bd_scan_yocto/__init__.py
bd_scan_yocto/bd_asyncdata.py
bd_scan_yocto/bd_process_bom.py
bd_scan_yocto/bd_scan_process.py
bd_scan_yocto/bdcomponentlist.py
bd_scan_yocto/config.py
bd_scan_yocto/global_values.py
bd_scan_yocto/main.py
bd_scan_yocto/process.py
bd_scan_yocto/utils.py
bd_scan_yocto-1.0.19.dist-info/LICENSE
bd_scan_yocto-1.0.19.dist-info/METADATA
bd_scan_yocto-1.0.19.dist-info/WHEEL
bd_scan_yocto-1.0.19.dist-info/entry_points.txt
bd_scan_yocto-1.0.19.dist-info/top_level.txt
bd_scan_yocto-1.0.19.dist-info/RECORD
