Metadata-Version: 2.1
Name: bd_scan_yocto
Version: 1.0.19
Summary: Process a built Yocto project to create a Black Duck project version
Author-email: Matthew Brady <mbrad@synopsys.com>
Project-URL: Homepage, https://github.com/matthewb66/bd_scan_yocto
Project-URL: Bug Tracker, https://github.com/matthewb66/bd_scan_yocto/issues
Classifier: Programming Language :: Python :: 3
Classifier: License :: OSI Approved :: Apache Software License
Classifier: Operating System :: OS Independent
Requires-Python: >=3.8
License-File: LICENSE
Requires-Dist: blackduck >=1.1.0
Requires-Dist: requests
Requires-Dist: aiohttp
